{"items":{"serializeList":[{"name":"hay","nr":115557.0},{"name":"wood","nr":161156.0},{"name":"carrot","nr":29880.0},{"name":"pumpkin","nr":3952.0},{"name":"cactus","nr":64593.0},{"name":"weird_substance","nr":6432.0},{"name":"gold","nr":15220.0},{"name":"water","nr":38123.0},{"name":"fertilizer","nr":9199.0}]},"dockedFiles":[],"minimizedFiles":["farmLayout","plant","sort","docs0","docs1"],"openFilePositions":[{"key":"farmLayout","value":{"x":-401.2708740234375,"y":2487.34130859375}},{"key":"main","value":{"x":-1087.872802734375,"y":1651.14697265625}},{"key":"plant","value":{"x":-389.013427734375,"y":2379.541748046875}},{"key":"sort","value":{"x":-352.04638671875,"y":2133.097900390625}},{"key":"docs0","value":{"x":944.4669189453125,"y":-125.83544921875}},{"key":"docs1","value":{"x":97.21923828125,"y":1091.283935546875}}],"openFileScrollPositions":[{"key":"farmLayout","value":1346.265869140625},{"key":"main","value":399.9989013671875},{"key":"plant","value":-0.0008544921875},{"key":"sort","value":1042.3621826171875}],"openFileSizes":[{"key":"farmLayout","value":{"x":0.0,"y":1260.4547119140625}},{"key":"main","value":{"x":0.0,"y":1114.8193359375}},{"key":"plant","value":{"x":1054.540283203125,"y":945.5591430664063}},{"key":"sort","value":{"x":0.0,"y":0.0}},{"key":"docs0","value":{"x":900.0,"y":700.0}},{"key":"docs1","value":{"x":900.0,"y":700.0}}],"openDocPages":[{"key":"docs0","value":"docs/output.md"},{"key":"docs1","value":"docs/unlocks/megafarm.md"}],"unlocks":["grass_6","soil","harvest","pass","do_a_flip","pet_the_piggy","grassland","hay","straw_hat","traffic_cone","while","true","false","break","continue","loops","speed_5","can_harvest","if","else","elif","change_hat","gray_hat","purple_hat","green_hat","brown_hat","hats","expand_6","move","north","south","east","west","for","range","get_world_size","wood","bush","entities","clear","plant","and","or","not","operators","carrots_5","carrot","till","can_trade","trade","items","carrot_seed","print","quick_print","unlocks","str","debug","get_entity_type","get_ground_type","grounds","get_pos_x","get_pos_y","none","num_items","num_unlocked","senses","watering_6","water","use_item","get_water","variables","functions","def","return","global","trees_5","tree","tree_hat","from","import","wizard_hat","pumpkins_4","pumpkin","pumpkin_seed","dead_pumpkin","carrot_hat","append","remove","pop","insert","len","list","lists","fertilizer_4","weird_substance","sunflower_seed","sunflower","power","get_active_power","measure","sunflowers","get_time","get_tick_count","timing","get_companion","polyculture","dicts","sets","add","dict","set","dictionaries","get_cost","costs","min","max","abs","random","utilities","hedge","treasure","gold","can_move","mazes_2","unlock","auto_unlock","swap","cactus_seed","cactus","cactus_hat","dinosaur","egg","bone","dinosaur_hat","apple","dinosaurs","gold_hat","megafarm_2","get_drone_id","num_drones","max_drones","wait_for","spawn_drone","has_finished","debug_2","set_execution_speed","set_world_size","simulation","simulate"],"version":3}